dbnl/__init__.py
dbnl/cli.py
dbnl/config.py
dbnl/errors.py
dbnl/logging.py
dbnl/py.typed
dbnl/sandbox.py
dbnl/warnings.py
dbnl/api/__init__.py
dbnl/api/stubs.py
dbnl/api/util.py
dbnl/api/version.py
dbnl/sdk/__init__.py
dbnl/sdk/core.py
dbnl/sdk/models.py
dbnl/sdk/semconv.py
dbnl/sdk/spans.py
dbnl/sdk/types.py
dbnl/sdk/util.py
dbnl-0.27.1.dist-info/licenses/LICENSE
dbnl-0.27.1.dist-info/licenses/NOTICE
dbnl-0.27.1.dist-info/METADATA
dbnl-0.27.1.dist-info/WHEEL
dbnl-0.27.1.dist-info/entry_points.txt
dbnl-0.27.1.dist-info/top_level.txt
dbnl-0.27.1.dist-info/RECORD
