Metadata-Version: 2.4
Name: dbnl
Version: 0.27.1
Summary: The dbnl Python client SDK
Author-email: Distributional <support@distributional.com>
License: 
Project-URL: Homepage, https://distributional.com
Project-URL: Source Code, https://github.com/dbnlAI/dbnl
Classifier: Programming Language :: Python :: 3
Classifier: License :: OSI Approved :: Apache Software License
Classifier: Operating System :: OS Independent
Requires-Python: >=3.9
License-File: LICENSE
License-File: NOTICE
Requires-Dist: click<9,>=8.0.0
Requires-Dist: dataclasses-json>=0.6.0
Requires-Dist: docker<8,>=7.0.0
Requires-Dist: requests<3.0.0,>=2.26.0
Requires-Dist: pandas>=1.0.0
Requires-Dist: pyarrow>=10.0.1
Requires-Dist: PyYAML>=6.0.0
Requires-Dist: typing_extensions>=1.0.0
Requires-Dist: opentelemetry-api<2,>=1
Requires-Dist: opentelemetry-proto<2,>=1
Requires-Dist: opentelemetry-sdk<2,>=1
Provides-Extra: dev
Requires-Dist: boto3-stubs; extra == "dev"
Requires-Dist: sphinx-markdown-builder<1,>=0.6.8; extra == "dev"
Requires-Dist: mypy<2,>=1.7.1; extra == "dev"
Requires-Dist: mypy-extensions<2,>=1.0.0; extra == "dev"
Requires-Dist: pandas-stubs>=2.0.3.230814; extra == "dev"
Requires-Dist: pre-commit<4,>=3.5.0; extra == "dev"
Requires-Dist: pyarrow-stubs>=10.0.1.7; extra == "dev"
Requires-Dist: pytest<8,>=7.4.3; extra == "dev"
Requires-Dist: pytest-mock<4,>=3.0.0; extra == "dev"
Requires-Dist: ruff<0.7,>=0.6.3; extra == "dev"
Requires-Dist: types-PyYAML<7,>=6.0.12; extra == "dev"
Requires-Dist: types-requests<3.0.0; python_version >= "3.10" and extra == "dev"
Requires-Dist: types-requests<2.31.0.7; python_version < "3.10" and extra == "dev"
Requires-Dist: semver<4; extra == "dev"
Requires-Dist: typing-extensions>=4.0.0; extra == "dev"
Requires-Dist: setuptools>=69.0.2; extra == "dev"
Requires-Dist: sphinx<8,>=7.0.0; extra == "dev"
Requires-Dist: sphinx-click<7,>=6.0.0; extra == "dev"
Dynamic: license-file
